{
  "$schema": "https://developer.microsoft.com/json-schemas/fabric/item/report/definition/visualContainer/2.10.0/schema.json",
  "name": "exec_header",
  "position": {
    "x": 40,
    "y": 20,
    "z": 2,
    "height": 90,
    "width": 900
  },
  "visual": {
    "visualType": "textbox",
    "objects": {
      "general": [
        {
          "properties": {
            "paragraphs": [
              {
                "textRuns": [
                  {
                    "value": "Executive Cockpit — SmartRetail Live",
                    "textStyle": {
                      "fontFamily": "Segoe UI",
                      "fontSize": "20pt",
                      "color": "#1F2A44",
                      "fontWeight": "bold"
                    }
                  }
                ]
              },
              {
                "textRuns": [
                  {
                    "value": "Real-time omnichannel control tower across stores, fulfillment, supply chain, and ML-driven risk signals.",
                    "textStyle": {
                      "fontFamily": "Segoe UI",
                      "fontSize": "10pt",
                      "color": "#5A6478"
                    }
                  }
                ]
              }
            ]
          }
        }
      ]
    },
    "drillFilterOtherVisuals": true
  }
}